SivParseHLK/__init__.py
SivParseHLK/cli.py
siv_scripts_parsehlk-0.3.0.dist-info/LICENSE.txt
siv_scripts_parsehlk-0.3.0.dist-info/METADATA
siv_scripts_parsehlk-0.3.0.dist-info/WHEEL
siv_scripts_parsehlk-0.3.0.dist-info/entry_points.txt
siv_scripts_parsehlk-0.3.0.dist-info/top_level.txt
siv_scripts_parsehlk-0.3.0.dist-info/RECORD
